partialtorch/_C.cpython-39-darwin.so
partialtorch/__init__.py
partialtorch/_masked_pair.py
partialtorch/extension.py
partialtorch/functional.py
partialtorch/linalg.py
partialtorch/types.py
partialtorch/version.py
partialtorch/csrc/MaskedPair.cpp
partialtorch/csrc/formatting.cpp
partialtorch/csrc/partialtorch.cpp
partialtorch/csrc/ops/binary.cpp
partialtorch/csrc/ops/conv.cpp
partialtorch/csrc/ops/experimental.cpp
partialtorch/csrc/ops/izero_div.cpp
partialtorch/csrc/ops/linear.cpp
partialtorch/csrc/ops/masked_adaptive_avg_pool.cpp
partialtorch/csrc/ops/masked_avg_pool.cpp
partialtorch/csrc/ops/nary.cpp
partialtorch/csrc/ops/normalization.cpp
partialtorch/csrc/ops/padding.cpp
partialtorch/csrc/ops/partial_binary.cpp
partialtorch/csrc/ops/partial_bitwise_binary.cpp
partialtorch/csrc/ops/partial_ternary.cpp
partialtorch/csrc/ops/partial_unary.cpp
partialtorch/csrc/ops/passthrough.cpp
partialtorch/csrc/ops/pooling.cpp
partialtorch/csrc/ops/random.cpp
partialtorch/csrc/ops/reduction.cpp
partialtorch/csrc/ops/ternary.cpp
partialtorch/csrc/ops/unary.cpp
partialtorch/csrc/ops/upsampling.cpp
partialtorch/csrc/ops/utilities.cpp
partialtorch/csrc/ops/autograd/izero_div_kernel.cpp
partialtorch/csrc/ops/autograd/masked_adaptive_avg_pool_kernel.cpp
partialtorch/csrc/ops/autograd/masked_avg_pool_kernel.cpp
partialtorch/csrc/ops/cpu/izero_div_kernel.cpp
partialtorch/csrc/ops/cpu/masked_adaptive_avg_pool_kernel.cpp
partialtorch/csrc/ops/cpu/masked_avg_pool_kernel.cpp
partialtorch/csrc/ops/cuda/izero_div_kernel.cu
partialtorch/csrc/ops/cuda/masked_adaptive_avg_pool_kernel.cu
partialtorch/csrc/ops/cuda/masked_avg_pool_kernel.cu
partialtorch/nn/__init__.py
partialtorch/nn/functional.py
partialtorch/nn/modules/__init__.py
partialtorch/nn/modules/activation.py
partialtorch/nn/modules/batchnorm.py
partialtorch/nn/modules/channelshuffle.py
partialtorch/nn/modules/container.py
partialtorch/nn/modules/conv.py
partialtorch/nn/modules/dropout.py
partialtorch/nn/modules/flatten.py
partialtorch-0.0.8.dist-info/LICENSE.txt
partialtorch-0.0.8.dist-info/METADATA
partialtorch-0.0.8.dist-info/WHEEL
partialtorch-0.0.8.dist-info/top_level.txt
partialtorch-0.0.8.dist-info/RECORD
