Metadata-Version: 2.1
Name: partialtorch
Version: 0.0.8
Summary: Masked and Partial Operations for PyTorch
Home-page: https://github.com/inspiros/partialtorch
Author: Hoang-Nhat Tran (inspiros)
Author-email: hnhat.tran@gmail.com
License: MIT
Project-URL: Source, https://github.com/inspiros/partialtorch
Keywords: masked_tensor,masked_operator,partial_operator
Classifier: Development Status :: 2 - Pre-Alpha
Classifier: Environment :: GPU :: NVIDIA CUDA :: 12 :: 12.1
Classifier: Intended Audience :: Developers
Classifier: Intended Audience :: Education
Classifier: Intended Audience :: Science/Research
Classifier: License :: OSI Approved :: MIT License
Classifier: Programming Language :: Python
Classifier: Programming Language :: Python :: 3
Classifier: Programming Language :: Python :: 3.8
Classifier: Programming Language :: Python :: 3.9
Classifier: Programming Language :: Python :: 3.10
Classifier: Programming Language :: Python :: 3.11
Classifier: Operating System :: OS Independent
Classifier: Topic :: Scientific/Engineering :: Mathematics
Classifier: Topic :: Scientific/Engineering :: Artificial Intelligence
Requires-Python: >=3.8
License-File: LICENSE.txt
Requires-Dist: torch>=2.1.0
